{
  "version": 1,
  "builtinSystems": [
    "harnejr-doctor",
    "loc-controller",
    "goal-topic-controller",
    "autonomous-healer",
    "workspace-memory",
    "context-efficiency"
  ],
  "servers": [],
  "statusLevels": [
    "configured",
    "command_exists",
    "executable",
    "env_present",
    "starts",
    "handshake_ok",
    "tool_smoke_ok"
  ],
  "policy": {
    "unknownRemoteMCPInAutonomousMode": "deny",
    "writeCapableMCPRequiresPolicy": true,
    "listToolsTimeoutMs": 5000
  }
}
